fuzzy_compare/__init__.py
fuzzy_compare/source.py
fuzzy_compare-1.1.dist-info/LICENSE
fuzzy_compare-1.1.dist-info/METADATA
fuzzy_compare-1.1.dist-info/WHEEL
fuzzy_compare-1.1.dist-info/top_level.txt
fuzzy_compare-1.1.dist-info/RECORD
