Metadata-Version: 2.1
Name: fuzzy-compare
Version: 1.1
Summary: The package includes a algorithm to calculate similarity between two strings
Home-page: https://github.com/AbdullahSaquib/fuzzy_compare
Author: Abdullah Saquib
Author-email: abdullahsaquib@gmail.com
License: MIT
Keywords: python,str,fuzzy,compare,strings,similarity
Platform: UNKNOWN
Classifier: Programming Language :: Python :: 3
Classifier: Operating System :: OS Independent
License-File: LICENSE
